limacalc/__init__.py
limacalc-0.1.dist-info/METADATA
limacalc-0.1.dist-info/WHEEL
limacalc-0.1.dist-info/license.txt
limacalc-0.1.dist-info/top_level.txt
limacalc-0.1.dist-info/RECORD
