Metadata-Version: 2.1
Name: limacalc
Version: 0.1
Summary: This is very basic calculator
Home-page: UNKNOWN
Author: Limadijaya
Author-email: limasuhendra@Gmail.com
License: UNKNOWN
Platform: UNKNOWN
Classifier: Programming Language :: Python :: 3
Classifier: License :: OSI Approved :: MIT License
Classifier: Operating System :: OS Independent
